uncrustify_objc.py
uncrustify_objc-1.6.dist-info/licenses/LICENSE
uncrustify_objc-1.6.dist-info/METADATA
uncrustify_objc-1.6.dist-info/WHEEL
uncrustify_objc-1.6.dist-info/entry_points.txt
uncrustify_objc-1.6.dist-info/top_level.txt
uncrustify_objc-1.6.dist-info/RECORD
