Metadata-Version: 2.4
Name: uncrustify-objc
Version: 1.6
Summary: Use uncrustify to format the objective-c files under the specified project path
Author-email: Will Han <xingheng.hax@qq.com>
License: MIT
Project-URL: Homepage, https://github.com/python-cli/uncrustify-objc
Keywords: uncrustify,objective-c,objc,code,beauty,format
Classifier: Development Status :: 4 - Beta
Classifier: Environment :: Console
Classifier: Intended Audience :: Developers
Classifier: Programming Language :: Python :: 3
Classifier: Programming Language :: Objective C
Classifier: Programming Language :: Unix Shell
Classifier: Topic :: Software Development :: Version Control
Classifier: Topic :: System :: Shells
Classifier: Topic :: Terminals
Classifier: Topic :: Text Processing :: Linguistic
Requires-Python: >=3.6
License-File: LICENSE
Requires-Dist: click
Requires-Dist: pathspec
Dynamic: license-file
